Egistic_Nav_Env/__init__.py
Egistic_Nav_Env/utils.py
Egistic_Nav_Env/envs/__init__.py
Egistic_Nav_Env/envs/nav_env.py
Egistic_Nav_Env/envs/nav_extrahard_env.py
nav_env-0.0.11.dist-info/METADATA
nav_env-0.0.11.dist-info/WHEEL
nav_env-0.0.11.dist-info/top_level.txt
nav_env-0.0.11.dist-info/RECORD
