Metadata-Version: 2.1
Name: nav-env
Version: 0.0.11
Summary: nav_env
Home-page: UNKNOWN
Author: Dias Bakhtiyarov
Author-email: dbakhtiyarov@nu.edu.kz
License: UNKNOWN
Platform: UNKNOWN
Classifier: Programming Language :: Python :: 3.6
Classifier: License :: OSI Approved :: MIT License
Classifier: Operating System :: OS Independent
Requires-Dist: gym
Requires-Dist: lgblkb-tools
